hippiehug/Chain.py
hippiehug/Nodes.py
hippiehug/RedisChain.py
hippiehug/RedisStore.py
hippiehug/S3Chain.py
hippiehug/Tree.py
hippiehug/__init__.py
hippiehug-0.0.9.dist-info/DESCRIPTION.rst
hippiehug-0.0.9.dist-info/METADATA
hippiehug-0.0.9.dist-info/RECORD
hippiehug-0.0.9.dist-info/WHEEL
hippiehug-0.0.9.dist-info/metadata.json
hippiehug-0.0.9.dist-info/top_level.txt
