Metadata-Version: 2.0
Name: hippiehug
Version: 0.0.9
Summary: A Merkle Tree implementation with a flexible storage backend.
Home-page: https://pypi.python.org/pypi/hippiehug/
Author: George Danezis
Author-email: g.danezis@ucl.ac.uk
License: 2-clause BSD
Platform: UNKNOWN
Requires-Dist: future (>=0.14.3)
Requires-Dist: msgpack-python (>=0.4.6)
Requires-Dist: pytest (>=2.6.4)
Requires-Dist: redis (>=2.0.0)
